CHANGES.txt
LICENSE.txt
MANIFEST.in
README.txt
hmac.py
setup.py
hmac.egg-info/PKG-INFO
hmac.egg-info/SOURCES.txt
hmac.egg-info/dependency_links.txt
hmac.egg-info/requires.txt
hmac.egg-info/top_level.txt
hmac.egg-info/zip-safe