Metadata-Version: 1.0
Name: hmac
Version: 20101005
Summary: HMAC (Keyed-Hashing for Message Authentication) Python module.
Home-page: UNKNOWN
Author: Laurence Rowe
Author-email: laurence@lrowe.co.uk
License: PSF license
Platform: UNKNOWN
Classifier: Development Status :: 5 - Production/Stable
Classifier: Intended Audience :: Developers
Classifier: License :: OSI Approved :: Python Software Foundation License
Classifier: Programming Language :: Python
Classifier: Topic :: Communications
Classifier: Topic :: Security :: Cryptography
